yandex_oauth/__init__.py
yandex_oauth/yao.py
yandex_oauth-0.0.4.dist-info/LICENSE
yandex_oauth-0.0.4.dist-info/METADATA
yandex_oauth-0.0.4.dist-info/WHEEL
yandex_oauth-0.0.4.dist-info/top_level.txt
yandex_oauth-0.0.4.dist-info/RECORD
